rapid_table/__init__.py
rapid_table/rapid_table.py
rapid_table/utils.py
rapid_table/models/en_ppstructure_mobile_v2_SLANet.onnx
rapid_table/table_matcher/__init__.py
rapid_table/table_matcher/matcher.py
rapid_table/table_matcher/utils.py
rapid_table/table_structure/__init__.py
rapid_table/table_structure/table_structure.py
rapid_table/table_structure/utils.py
rapid_table-3.6.dist-info/METADATA
rapid_table-3.6.dist-info/WHEEL
rapid_table-3.6.dist-info/entry_points.txt
rapid_table-3.6.dist-info/top_level.txt
rapid_table-3.6.dist-info/RECORD
