Metadata-Version: 2.1
Name: rapid-table
Version: 3.6
Summary: Tools for parsing table structures based ONNXRuntime.
Home-page: https://github.com/RapidAI/RapidStructure
Author: SWHL
Author-email: liekkaskono@163.com
License: Apache-2.0
Keywords: ppstructure,table,rapidocr,rapid_table
Platform: Any
Classifier: Programming Language :: Python :: 3.6
Classifier: Programming Language :: Python :: 3.7
Classifier: Programming Language :: Python :: 3.8
Classifier: Programming Language :: Python :: 3.9
Classifier: Programming Language :: Python :: 3.10
Classifier: Programming Language :: Python :: 3.11
Requires-Python: >=3.6,<=3.11
Requires-Dist: onnxruntime (>=1.7.0)
Requires-Dist: PyYAML (>=6.0)
Requires-Dist: opencv-python (>=4.5.1.48)
Requires-Dist: numpy (>=1.21.6)
Requires-Dist: rapidocr-onnxruntime (>=1.1.18)
Requires-Dist: Pillow
